cfnet/__init__.py
cfnet/_ckpt_manager.py
cfnet/_modidx.py
cfnet/_nbdev.py
cfnet/datasets.py
cfnet/evaluate.py
cfnet/import_essentials.py
cfnet/interfaces.py
cfnet/logger.py
cfnet/module.py
cfnet/nets.py
cfnet/train.py
cfnet/training_module.py
cfnet/utils.py
cfnet/data/__init__.py
cfnet/data/loader.py
cfnet/data/module.py
cfnet/methods/__init__.py
cfnet/methods/base.py
cfnet/methods/counternet.py
cfnet/methods/diverse.py
cfnet/methods/proto.py
cfnet/methods/vae_cf.py
cfnet/methods/vanilla.py
relax/__init__.py
relax/_ckpt_manager.py
relax/_modidx.py
relax/evaluate.py
relax/import_essentials.py
relax/logger.py
relax/module.py
relax/trainer.py
relax/utils.py
relax/data/__init__.py
relax/data/loader.py
relax/data/module.py
relax/methods/__init__.py
relax/methods/base.py
relax/methods/counternet.py
relax/methods/diverse.py
relax/methods/proto.py
relax/methods/vanilla.py
jax_rex-0.0.11.dist-info/LICENSE
jax_rex-0.0.11.dist-info/METADATA
jax_rex-0.0.11.dist-info/WHEEL
jax_rex-0.0.11.dist-info/entry_points.txt
jax_rex-0.0.11.dist-info/top_level.txt
jax_rex-0.0.11.dist-info/RECORD
