Metadata-Version: 2.1
Name: jax-rex
Version: 0.0.11
Summary: Jax-based Recourse Explanation Library
Home-page: https://github.com/birkhoffg/cfnet/tree/master/
Author: BirkhoffG
Author-email: 26811230+BirkhoffG@users.noreply.github.com
License: Apache Software License 2.0
Keywords: Jax,Recourse,Explanation,Interpretability,Machine Learning
Classifier: Development Status :: 3 - Alpha
Classifier: Intended Audience :: Developers
Classifier: Natural Language :: English
Classifier: Programming Language :: Python :: 3.7
Classifier: Programming Language :: Python :: 3.8
Classifier: Programming Language :: Python :: 3.9
Classifier: Programming Language :: Python :: 3.10
Classifier: License :: OSI Approved :: Apache Software License
Requires-Python: >=3.7
License-File: LICENSE
Requires-Dist: matplotlib
Requires-Dist: scikit-learn
Requires-Dist: pandas
Requires-Dist: nbdev
Requires-Dist: jupyter
Requires-Dist: dm-haiku
Requires-Dist: test-tube
Requires-Dist: jax[cpu]
Requires-Dist: tqdm
Requires-Dist: optax
Requires-Dist: pydantic (<2,>=1.9.0)
Requires-Dist: deprecation
Provides-Extra: dev
Requires-Dist: torch (>=1.7.0) ; extra == 'dev'
